dispatching.py
Dispatching-1.4.0.dist-info/RECORD
Dispatching-1.4.0.dist-info/METADATA
Dispatching-1.4.0.dist-info/DESCRIPTION.rst
Dispatching-1.4.0.dist-info/WHEEL
Dispatching-1.4.0.dist-info/top_level.txt
Dispatching-1.4.0.dist-info/pydist.json
