Metadata-Version: 2.0
Name: Dispatching
Version: 1.4.0
Summary: A library for overloading python functions
Home-page: https://github.com/Lucretiel/Dispatch
Author: Nathan West
Author-email: UNKNOWN
License: LGPLv3
Platform: any
Classifier: Development Status :: 4 - Beta
Classifier: Intended Audience :: Developers
Classifier: License :: OSI Approved :: GNU Lesser General Public License v3 (LGPLv3)
Classifier: Programming Language :: Python :: 3
Classifier: Programming Language :: Python :: 3.3
Classifier: Topic :: Software Development
Classifier: Topic :: Software Development :: Libraries
Classifier: Topic :: Software Development :: Libraries :: Python Modules
